puter/__init__.py
puter/chat_completion.py
puter/client.py
puter-0.0.13.dist-info/LICENSE
puter-0.0.13.dist-info/METADATA
puter-0.0.13.dist-info/WHEEL
puter-0.0.13.dist-info/top_level.txt
puter-0.0.13.dist-info/RECORD
