Metadata-Version: 2.1
Name: puter
Version: 0.0.13
Summary: A Python client for Puter AI API - free access to GPT-4 and Claude
Home-page: https://github.com/Nemyam/puter
Author: Nemyam
Author-email: nemyam0@gmail.com
Keywords: ai,gpt4,claude,puter,chatbot,llm,gpt-4,anthropic
Classifier: Programming Language :: Python :: 3
Classifier: License :: OSI Approved :: MIT License
Classifier: Operating System :: OS Independent
Classifier: Development Status :: 4 - Beta
Classifier: Intended Audience :: Developers
Classifier: Topic :: Software Development :: Libraries :: Python Modules
Requires-Python: >=3.7
License-File: LICENSE
Requires-Dist: requests>=2.25.0
Requires-Dist: rich>=10.0.0
